{
  "$schema": "https://ui.shadcn.com/schema/registry-item.json",
  "name": "old-maps-timeline",
  "title": "Old Maps Timeline",
  "description": "MapLibre historical map explorer recreating the OldMapsOnline experience: a bottom timeline, a linked results sidebar, and map coverage footprints that all stay in sync on hover and selection.",
  "dependencies": [
    "lucide-react"
  ],
  "registryDependencies": [
    "@mapcn/map"
  ],
  "files": [
    {
      "path": "src/registry/blocks/old-maps-timeline/page.tsx",
      "content": "\"use client\";\n\nimport { useMemo, useRef, useState } from \"react\";\nimport { PanelLeftOpen } from \"lucide-react\";\n\nimport {\n  Map,\n  MapControls,\n  MapMarker,\n  MarkerContent,\n  MarkerTooltip,\n  type MapRef,\n} from \"@/components/ui/map\";\nimport { cn } from \"@/lib/utils\";\nimport {\n  historicalMaps,\n  mapBounds,\n  type HistoricalMapRecord,\n} from \"./data\";\nimport { OldMapsTimeline } from \"./components/old-maps-timeline\";\nimport { ResultsSidebar } from \"./components/results-sidebar\";\nimport { MapFootprints } from \"./components/map-footprints\";\n\nfunction yearMatches(map: HistoricalMapRecord, year: number) {\n  return year >= map.range[0] && year <= map.range[1];\n}\n\nfunction nearestMapForYear(year: number) {\n  return historicalMaps.reduce((nearest, map) =>\n    Math.abs(map.year - year) < Math.abs(nearest.year - year) ? map : nearest,\n  );\n}\n\nfunction matchesQuery(map: HistoricalMapRecord, query: string) {\n  if (!query) return true;\n  const haystack =\n    `${map.title} ${map.place} ${map.author} ${map.archive}`.toLowerCase();\n  return haystack.includes(query);\n}\n\nexport default function Page() {\n  const mapRef = useRef<MapRef>(null);\n  const [year, setYear] = useState(1860);\n  const [selectedMapId, setSelectedMapId] = useState(\"republica-mexicana\");\n  const [hoveredMapId, setHoveredMapId] = useState<string | null>(null);\n  const [query, setQuery] = useState(\"\");\n  const [mobileOpen, setMobileOpen] = useState(false);\n\n  const normalizedQuery = query.trim().toLowerCase();\n\n  // Maps published within the selected year window, filtered by the search.\n  // Drives the sidebar list, the map markers and the highlighted footprints.\n  const visibleMaps = useMemo(() => {\n    return historicalMaps\n      .filter(\n        (map) => yearMatches(map, year) && matchesQuery(map, normalizedQuery),\n      )\n      .sort(\n        (a, b) =>\n          Math.abs(a.year - year) - Math.abs(b.year - year) ||\n          a.title.localeCompare(b.title),\n      );\n  }, [year, normalizedQuery]);\n\n  const selectedMap =\n    historicalMaps.find((map) => map.id === selectedMapId) ??\n    nearestMapForYear(year);\n\n  // Keep the selected sheet's footprint on the map even if the search/year\n  // would otherwise hide it.\n  const footprintMaps = useMemo(() => {\n    if (visibleMaps.some((map) => map.id === selectedMap.id)) {\n      return visibleMaps;\n    }\n    return [...visibleMaps, selectedMap];\n  }, [visibleMaps, selectedMap]);\n\n  function selectMap(mapId: string) {\n    const next = historicalMaps.find((map) => map.id === mapId);\n    if (!next) return;\n    setSelectedMapId(mapId);\n    setYear(next.year);\n    setMobileOpen(false);\n    mapRef.current?.fitBounds(mapBounds(next), {\n      padding: { top: 64, bottom: 170, left: 48, right: 48 },\n      maxZoom: 7.5,\n      duration: 900,\n    });\n  }\n\n  return (\n    <div className=\"bg-background p-4 sm:p-6\">\n      <div className=\"relative mx-auto flex h-[760px] max-w-7xl overflow-hidden rounded-lg border shadow-sm\">\n        {mobileOpen ? (\n          <button\n            type=\"button\"\n            aria-label=\"Close results\"\n            onClick={() => setMobileOpen(false)}\n            className=\"absolute inset-0 z-30 bg-black/20 md:hidden\"\n          />\n        ) : null}\n\n        <ResultsSidebar\n          className={cn(\n            \"absolute inset-y-0 left-0 z-40 max-w-[340px] transition-transform duration-300 md:relative md:z-auto md:max-w-none md:translate-x-0\",\n            mobileOpen ? \"translate-x-0 shadow-xl\" : \"-translate-x-full md:flex\",\n          )}\n          maps={visibleMaps}\n          totalCount={historicalMaps.length}\n          year={year}\n          query={query}\n          selectedMapId={selectedMap.id}\n          hoveredMapId={hoveredMapId}\n          onQueryChange={setQuery}\n          onSelectMap={selectMap}\n          onHoverMap={setHoveredMapId}\n          onClose={() => setMobileOpen(false)}\n        />\n\n        <div className=\"relative flex-1\">\n          <Map\n            ref={mapRef}\n            center={[-101, 22]}\n            zoom={4.6}\n            minZoom={1}\n            maxZoom={10}\n            styles={{\n              light: \"https://tiles.openfreemap.org/styles/bright\",\n              dark: \"https://tiles.openfreemap.org/styles/dark\",\n            }}\n          >\n            <MapControls position=\"top-right\" />\n\n            <MapFootprints\n              maps={footprintMaps}\n              selectedMapId={selectedMap.id}\n              hoveredMapId={hoveredMapId}\n              onSelectMap={selectMap}\n              onHoverMap={setHoveredMapId}\n            />\n\n            <button\n              type=\"button\"\n              onClick={() => setMobileOpen(true)}\n              className=\"bg-background/90 absolute top-4 left-4 z-20 flex items-center gap-2 rounded-md border px-3 py-2 text-sm font-medium shadow-sm backdrop-blur md:hidden\"\n            >\n              <PanelLeftOpen className=\"size-4\" />\n              {visibleMaps.length} results\n            </button>\n\n            {visibleMaps.map((map) => {\n              const selected = map.id === selectedMap.id;\n              const hovered = !selected && map.id === hoveredMapId;\n              return (\n                <MapMarker\n                  key={map.id}\n                  longitude={map.lng}\n                  latitude={map.lat}\n                  offset={[0, 8]}\n                >\n                  <MarkerContent>\n                    <span\n                      role=\"button\"\n                      tabIndex={0}\n                      onClick={() => selectMap(map.id)}\n                      onMouseEnter={() => setHoveredMapId(map.id)}\n                      onMouseLeave={() => setHoveredMapId(null)}\n                      onKeyDown={(event) => {\n                        if (event.key === \"Enter\" || event.key === \" \") {\n                          event.preventDefault();\n                          selectMap(map.id);\n                        }\n                      }}\n                      className=\"grid place-items-center\"\n                      aria-label={map.title}\n                    >\n                      <span\n                        className={cn(\n                          \"grid place-items-center rounded-full border-2 border-white shadow-md transition-all\",\n                          selected\n                            ? \"size-9 bg-[#ab1000]\"\n                            : hovered\n                              ? \"size-7 bg-[#e7903a]\"\n                              : \"size-5 bg-[#675c44]\",\n                        )}\n                      >\n                        <span className=\"size-2 rounded-full bg-white\" />\n                      </span>\n                    </span>\n                  </MarkerContent>\n                  <MarkerTooltip\n                    offset={16}\n                    className=\"bg-background text-foreground border px-3 py-2\"\n                  >\n                    <p className=\"text-sm font-medium\">{map.title}</p>\n                    <p className=\"text-muted-foreground mt-1 text-xs\">\n                      {map.place} · {map.year} · {map.author}\n                    </p>\n                  </MarkerTooltip>\n                </MapMarker>\n              );\n            })}\n\n            <OldMapsTimeline\n              year={year}\n              maps={historicalMaps}\n              selectedMapId={selectedMap.id}\n              hoveredMapId={hoveredMapId}\n              onYearChange={setYear}\n              onSelectMap={selectMap}\n              onHoverMap={setHoveredMapId}\n            />\n          </Map>\n        </div>\n      </div>\n    </div>\n  );\n}\n",
      "type": "registry:page",
      "target": "app/old-maps/page.tsx"
    },
    {
      "path": "src/registry/blocks/old-maps-timeline/data.ts",
      "content": "\"use client\";\n\nexport type HistoricalMapRecord = {\n  id: string;\n  title: string;\n  place: string;\n  /** Publication year used to position the map on the timeline. */\n  year: number;\n  /** Inclusive [from, to] range the sheet is considered relevant for. */\n  range: [number, number];\n  /** Footprint centre — longitude. */\n  lng: number;\n  /** Footprint centre — latitude. */\n  lat: number;\n  /** Footprint size in degrees, [width, height], centred on lng/lat. */\n  coverage: [number, number];\n  /** Cartographer / publisher shown on the result card. */\n  author: string;\n  /** Holding institution / collection. */\n  archive: string;\n  scale: string;\n  description: string;\n};\n\nexport const historicalMaps: HistoricalMapRecord[] = [\n  {\n    id: \"central-america-dispatch\",\n    title: \"Central America (southern part), including Yucatan\",\n    place: \"Yucatán\",\n    year: 1863,\n    range: [1840, 1870],\n    lng: -90.3,\n    lat: 18.7,\n    coverage: [11, 8],\n    author: \"Theodor Ettling — Weekly Dispatch Atlas\",\n    archive: \"David Rumsey Map Collection\",\n    scale: \"1:6 500 000\",\n    description: \"Regional sheet covering Yucatán and the southern gulf.\",\n  },\n  {\n    id: \"republica-mexicana\",\n    title: \"Republica Mexicana\",\n    place: \"Mexico\",\n    year: 1867,\n    range: [1850, 1885],\n    lng: -101.5,\n    lat: 23.5,\n    coverage: [22, 17],\n    author: \"Victor Debray\",\n    archive: \"Biblioteca Nacional de México\",\n    scale: \"1:1 267 200\",\n    description: \"National map with state boundaries and major routes.\",\n  },\n  {\n    id: \"mexico-central-america\",\n    title: \"Mexico and Central America\",\n    place: \"Mexico\",\n    year: 1864,\n    range: [1845, 1880],\n    lng: -99.5,\n    lat: 19.4,\n    coverage: [24, 18],\n    author: \"William Hughes\",\n    archive: \"British Library\",\n    scale: \"1:6 250 000\",\n    description: \"Political geography of Mexico and Central America.\",\n  },\n  {\n    id: \"mexico-guatemala\",\n    title: \"Mexico and Guatemala\",\n    place: \"Chiapas\",\n    year: 1848,\n    range: [1835, 1865],\n    lng: -92.4,\n    lat: 16.9,\n    coverage: [10, 8],\n    author: \"John Sharpe\",\n    archive: \"Library of Congress\",\n    scale: \"1:8 400 000\",\n    description: \"Borderland sheet with terrain hachures and ports.\",\n  },\n  {\n    id: \"schonberg-mexico\",\n    title: \"Schonberg's Map of Mexico\",\n    place: \"Mexico\",\n    year: 1867,\n    range: [1855, 1885],\n    lng: -103.4,\n    lat: 20.7,\n    coverage: [20, 15],\n    author: \"Schonberg & Co.\",\n    archive: \"Stanford Libraries\",\n    scale: \"1:6 311 000\",\n    description: \"Commercial atlas sheet with dense place labels.\",\n  },\n  {\n    id: \"colby-mexico\",\n    title: \"Mexico\",\n    place: \"Mexico\",\n    year: 1856,\n    range: [1840, 1872],\n    lng: -106.2,\n    lat: 25.4,\n    coverage: [18, 14],\n    author: \"Charles A. Colby\",\n    archive: \"David Rumsey Map Collection\",\n    scale: \"1:10 500 000\",\n    description: \"Mid-century reference map of Mexico and surrounding waters.\",\n  },\n  {\n    id: \"johnson-mexico\",\n    title: \"Mexico\",\n    place: \"Veracruz\",\n    year: 1864,\n    range: [1850, 1880],\n    lng: -97.6,\n    lat: 21.2,\n    coverage: [16, 13],\n    author: \"A. J. Johnson\",\n    archive: \"Library of Congress\",\n    scale: \"1:8 218 000\",\n    description: \"Atlas plate with inset coastal and regional detail.\",\n  },\n  {\n    id: \"tanner-mexico\",\n    title: \"A Map of Mexico & Guatemala\",\n    place: \"Mexico\",\n    year: 1834,\n    range: [1825, 1855],\n    lng: -100.8,\n    lat: 22.4,\n    coverage: [23, 17],\n    author: \"Henry S. Tanner\",\n    archive: \"Library of Congress\",\n    scale: \"1:5 700 000\",\n    description: \"Early republican-era map with provincial divisions.\",\n  },\n  {\n    id: \"valle-de-mexico\",\n    title: \"Valle de México\",\n    place: \"Ciudad de México\",\n    year: 1873,\n    range: [1860, 1890],\n    lng: -99.13,\n    lat: 19.43,\n    coverage: [2.4, 2],\n    author: \"Antonio García Cubas\",\n    archive: \"Biblioteca Nacional de México\",\n    scale: \"1:250 000\",\n    description: \"Detailed survey of the basin of Mexico and its lakes.\",\n  },\n  {\n    id: \"puebla-tlaxcala\",\n    title: \"Estado de Puebla y Tlaxcala\",\n    place: \"Puebla\",\n    year: 1858,\n    range: [1845, 1875],\n    lng: -98.0,\n    lat: 19.0,\n    coverage: [3.5, 3],\n    author: \"Manuel Orozco y Berra\",\n    archive: \"Biblioteca Nacional de México\",\n    scale: \"1:500 000\",\n    description: \"State sheet with road network and elevation hachures.\",\n  },\n  {\n    id: \"yucatan-peninsula\",\n    title: \"Plano de la Península de Yucatán\",\n    place: \"Yucatán\",\n    year: 1878,\n    range: [1865, 1895],\n    lng: -89.0,\n    lat: 20.2,\n    coverage: [6, 5],\n    author: \"Comisión Geográfica Exploradora\",\n    archive: \"Mapoteca Manuel Orozco y Berra\",\n    scale: \"1:1 000 000\",\n    description: \"Peninsular survey with haciendas and coastal soundings.\",\n  },\n  {\n    id: \"oaxaca-istmo\",\n    title: \"Istmo de Tehuantepec\",\n    place: \"Oaxaca\",\n    year: 1851,\n    range: [1842, 1868],\n    lng: -94.8,\n    lat: 16.6,\n    coverage: [4, 4],\n    author: \"J. J. Williams\",\n    archive: \"American Geographical Society Library\",\n    scale: \"1:600 000\",\n    description: \"Survey of the isthmus for a proposed inter-ocean route.\",\n  },\n  {\n    id: \"norte-frontera\",\n    title: \"Mapa de la Frontera del Norte\",\n    place: \"Chihuahua\",\n    year: 1886,\n    range: [1872, 1900],\n    lng: -106.0,\n    lat: 28.6,\n    coverage: [14, 9],\n    author: \"Comisión Geográfica Exploradora\",\n    archive: \"Mapoteca Manuel Orozco y Berra\",\n    scale: \"1:2 000 000\",\n    description: \"Northern frontier states with railroads and mining districts.\",\n  },\n  {\n    id: \"michoacan-jalisco\",\n    title: \"Estados de Michoacán y Jalisco\",\n    place: \"Jalisco\",\n    year: 1869,\n    range: [1858, 1882],\n    lng: -102.6,\n    lat: 20.0,\n    coverage: [6, 5],\n    author: \"Antonio García Cubas\",\n    archive: \"David Rumsey Map Collection\",\n    scale: \"1:800 000\",\n    description: \"West-central states with lakes, volcanoes, and parishes.\",\n  },\n];\n\nexport const timelineBounds = {\n  min: 1500,\n  max: 2002,\n  step: 1,\n};\n\n/** Footprint corners for a record, derived from its centre and coverage. */\nexport function mapBounds(\n  map: HistoricalMapRecord,\n): [[number, number], [number, number]] {\n  const [w, h] = map.coverage;\n  return [\n    [map.lng - w / 2, map.lat - h / 2],\n    [map.lng + w / 2, map.lat + h / 2],\n  ];\n}\n\nexport type FootprintState = \"default\" | \"hovered\" | \"selected\";\n\n/** GeoJSON polygons for every footprint, tagged with their current state. */\nexport function footprintCollection(\n  maps: HistoricalMapRecord[],\n  selectedId: string | null,\n  hoveredId: string | null,\n): GeoJSON.FeatureCollection<GeoJSON.Polygon> {\n  return {\n    type: \"FeatureCollection\",\n    features: maps.map((map) => {\n      const [[west, south], [east, north]] = mapBounds(map);\n      const state: FootprintState =\n        map.id === selectedId\n          ? \"selected\"\n          : map.id === hoveredId\n            ? \"hovered\"\n            : \"default\";\n      return {\n        type: \"Feature\",\n        properties: { id: map.id, title: map.title, state },\n        geometry: {\n          type: \"Polygon\",\n          coordinates: [\n            [\n              [west, south],\n              [east, south],\n              [east, north],\n              [west, north],\n              [west, south],\n            ],\n          ],\n        },\n      };\n    }),\n  };\n}\n",
      "type": "registry:component",
      "target": "app/old-maps/data.ts"
    },
    {
      "path": "src/registry/blocks/old-maps-timeline/components/old-maps-timeline.tsx",
      "content": "\"use client\";\n\nimport { useMemo, useRef } from \"react\";\nimport {\n  ChevronDown,\n  ChevronLeft,\n  ChevronRight,\n  ChevronUp,\n} from \"lucide-react\";\n\nimport { cn } from \"@/lib/utils\";\nimport { timelineBounds, type HistoricalMapRecord } from \"../data\";\n\ntype OldMapsTimelineProps = {\n  year: number;\n  maps: HistoricalMapRecord[];\n  selectedMapId: string;\n  hoveredMapId?: string | null;\n  className?: string;\n  onYearChange: (year: number) => void;\n  onSelectMap: (mapId: string) => void;\n  onHoverMap?: (mapId: string | null) => void;\n};\n\n// OldMapsOnline palette — kept as literals so the timeline owns its look.\nconst RED = \"#ab1000\";\nconst INK = \"#675c44\";\n\nconst YEAR_WIDTH = 10;\nconst MIN = timelineBounds.min;\nconst MAX = timelineBounds.max;\nconst SPAN = MAX - MIN;\nconst STRIP_WIDTH = SPAN * YEAR_WIDTH;\n\n// Vertical anchors, measured from the bottom of the timeline (px).\nconst BASELINE = 26;\nconst LABEL_LEVELS = [46, 70, 94];\n\nfunction clampYear(year: number) {\n  return Math.min(MAX, Math.max(MIN, year));\n}\n\nfunction yearToOffset(year: number) {\n  return (year - MIN) * YEAR_WIDTH;\n}\n\n/** A tiny Mexican tricolour standing in for OldMapsOnline's country flags. */\nfunction MiniFlag() {\n  return (\n    <span className=\"flex h-[9px] w-[13px] overflow-hidden rounded-[1px] border border-black/20 shadow-sm\">\n      <span className=\"flex-1 bg-[#006847]\" />\n      <span className=\"flex-1 bg-white\" />\n      <span className=\"flex-1 bg-[#ce1126]\" />\n    </span>\n  );\n}\n\nexport function OldMapsTimeline({\n  year,\n  maps,\n  selectedMapId,\n  hoveredMapId,\n  className,\n  onYearChange,\n  onSelectMap,\n  onHoverMap,\n}: OldMapsTimelineProps) {\n  const dragRef = useRef<{ x: number; year: number } | null>(null);\n\n  const currentOffset = yearToOffset(year);\n\n  const years = useMemo(\n    () => Array.from({ length: SPAN + 1 }, (_, index) => MIN + index),\n    [],\n  );\n\n  // Stable label rows: sort by year, then stagger across three heights.\n  const labelled = useMemo(() => {\n    return [...maps]\n      .sort((a, b) => a.year - b.year)\n      .map((map, index) => ({\n        map,\n        level: LABEL_LEVELS[index % LABEL_LEVELS.length],\n      }));\n  }, [maps]);\n\n  const sortedByYear = useMemo(\n    () => [...maps].sort((a, b) => a.year - b.year),\n    [maps],\n  );\n  const prevMap = [...sortedByYear].reverse().find((map) => map.year < year);\n  const nextMap = sortedByYear.find((map) => map.year > year);\n\n  function startDrag(event: React.PointerEvent<HTMLDivElement>) {\n    dragRef.current = { x: event.clientX, year };\n    event.currentTarget.setPointerCapture(event.pointerId);\n  }\n  function moveDrag(event: React.PointerEvent<HTMLDivElement>) {\n    if (!dragRef.current) return;\n    const dx = event.clientX - dragRef.current.x;\n    onYearChange(clampYear(Math.round(dragRef.current.year - dx / YEAR_WIDTH)));\n  }\n  function endDrag() {\n    dragRef.current = null;\n  }\n\n  return (\n    <div\n      className={cn(\n        \"absolute inset-x-0 bottom-0 z-20 h-[156px] select-none\",\n        className,\n      )}\n    >\n      {/* Parchment fade — kept constant across themes so the OldMapsOnline\n          ruler stays readable on both light and dark basemaps. */}\n      <div className=\"pointer-events-none absolute inset-0 bg-[linear-gradient(0deg,#fdfaf2_0%,#fdfaf2_38%,rgba(253,250,242,0.85)_62%,rgba(253,250,242,0)_100%)]\" />\n\n      {/* Centre guide connecting the year flag to the handle. */}\n      <div\n        className=\"pointer-events-none absolute left-1/2 w-px -translate-x-1/2\"\n        style={{ bottom: BASELINE, height: 78, backgroundColor: `${RED}33` }}\n      />\n\n      {/* Draggable ruler with ticks, year labels and map flags. */}\n      <div\n        className=\"absolute inset-x-0 bottom-0 h-[120px] cursor-grab touch-none overflow-hidden px-[50%] [mask:linear-gradient(90deg,rgba(0,0,0,0)_0%,#000_6%,#000_94%,rgba(0,0,0,0)_100%)] active:cursor-grabbing\"\n        onPointerDown={startDrag}\n        onPointerMove={moveDrag}\n        onPointerUp={endDrag}\n        onPointerLeave={endDrag}\n      >\n        <div\n          className=\"relative h-full transition-transform duration-200 ease-out\"\n          style={{\n            width: STRIP_WIDTH,\n            transform: `translateX(${-currentOffset}px)`,\n          }}\n        >\n          <div\n            className=\"absolute left-0\"\n            style={{\n              bottom: BASELINE,\n              width: STRIP_WIDTH,\n              height: 1,\n              backgroundColor: `${INK}66`,\n            }}\n          />\n\n          {years.map((tickYear) => {\n            const major = tickYear % 50 === 0;\n            const medium = tickYear % 10 === 0;\n            return (\n              <div\n                key={tickYear}\n                className=\"absolute\"\n                style={{ left: yearToOffset(tickYear), bottom: BASELINE }}\n              >\n                <div\n                  style={{\n                    width: 1,\n                    height: major ? 16 : medium ? 9 : 5,\n                    backgroundColor: major ? INK : `${INK}99`,\n                  }}\n                />\n                {major ? (\n                  <span\n                    className=\"absolute top-[18px] -translate-x-1/2 text-xs tabular-nums\"\n                    style={{ color: INK }}\n                  >\n                    {tickYear}\n                  </span>\n                ) : null}\n              </div>\n            );\n          })}\n\n          {labelled.map(({ map, level }) => {\n            const selected = map.id === selectedMapId;\n            const hovered = map.id === hoveredMapId;\n            const distance = Math.abs(map.year - year);\n            const opacity = selected\n              ? 1\n              : Math.max(0.4, 1 - distance / 70);\n            return (\n              <button\n                key={map.id}\n                type=\"button\"\n                aria-label={`${map.title}, ${map.year}`}\n                onPointerDown={(event) => event.stopPropagation()}\n                onClick={(event) => {\n                  event.stopPropagation();\n                  onSelectMap(map.id);\n                }}\n                onPointerEnter={() => onHoverMap?.(map.id)}\n                onPointerLeave={() => onHoverMap?.(null)}\n                className=\"absolute flex -translate-x-1/2 flex-col items-center gap-0.5\"\n                style={{ left: yearToOffset(map.year), bottom: level, opacity }}\n              >\n                <span\n                  className=\"absolute top-full left-1/2 w-px -translate-x-1/2\"\n                  style={{\n                    height: level - BASELINE,\n                    backgroundColor: selected ? RED : `${INK}59`,\n                  }}\n                />\n                <MiniFlag />\n                <span\n                  className={cn(\n                    \"max-w-[92px] truncate text-[10px] leading-tight font-medium\",\n                    (selected || hovered) && \"font-semibold\",\n                  )}\n                  style={{ color: selected ? RED : INK }}\n                >\n                  {map.place}\n                </span>\n                <span\n                  className=\"text-[10px] leading-none tabular-nums\"\n                  style={{ color: selected ? RED : `${INK}cc` }}\n                >\n                  {map.year}\n                </span>\n              </button>\n            );\n          })}\n        </div>\n      </div>\n\n      {/* Position handle with previous / next map arrows (fixed at centre). */}\n      <div\n        className=\"absolute left-1/2 z-20 flex -translate-x-1/2 items-center gap-2\"\n        style={{ bottom: BASELINE - 14 }}\n      >\n        <button\n          type=\"button\"\n          aria-label=\"Previous map\"\n          disabled={!prevMap}\n          onClick={() => prevMap && onSelectMap(prevMap.id)}\n          className=\"grid size-7 place-items-center rounded-full text-white shadow-sm transition disabled:opacity-30\"\n          style={{ backgroundColor: RED }}\n        >\n          <ChevronLeft className=\"size-4\" />\n        </button>\n        <span\n          className=\"size-7 rounded-full border-[3px] bg-white shadow-md\"\n          style={{ borderColor: RED }}\n        />\n        <button\n          type=\"button\"\n          aria-label=\"Next map\"\n          disabled={!nextMap}\n          onClick={() => nextMap && onSelectMap(nextMap.id)}\n          className=\"grid size-7 place-items-center rounded-full text-white shadow-sm transition disabled:opacity-30\"\n          style={{ backgroundColor: RED }}\n        >\n          <ChevronRight className=\"size-4\" />\n        </button>\n      </div>\n\n      {/* Centred year flag with step arrows and a downward pointer. */}\n      <div className=\"absolute top-0 left-1/2 z-30 flex -translate-x-1/2 flex-col items-center\">\n        <div\n          className=\"flex flex-col items-center rounded-md px-3 py-1 shadow-[0_3px_8px_rgba(0,0,0,0.25)]\"\n          style={{ backgroundColor: RED }}\n        >\n          <button\n            type=\"button\"\n            aria-label=\"Increase year\"\n            onClick={() => onYearChange(clampYear(year + 1))}\n            className=\"-mb-1 text-white/70 transition-colors hover:text-white\"\n          >\n            <ChevronUp className=\"size-4\" />\n          </button>\n          <input\n            aria-label=\"Selected year\"\n            type=\"number\"\n            min={MIN}\n            max={MAX}\n            inputMode=\"numeric\"\n            value={year}\n            onChange={(event) => {\n              const next = Number(event.target.value);\n              if (Number.isFinite(next)) onYearChange(clampYear(next));\n            }}\n            className=\"w-[60px] [appearance:textfield] bg-transparent text-center text-lg font-semibold text-white outline-none [&::-webkit-inner-spin-button]:appearance-none [&::-webkit-outer-spin-button]:appearance-none\"\n          />\n          <button\n            type=\"button\"\n            aria-label=\"Decrease year\"\n            onClick={() => onYearChange(clampYear(year - 1))}\n            className=\"-mt-1 text-white/70 transition-colors hover:text-white\"\n          >\n            <ChevronDown className=\"size-4\" />\n          </button>\n        </div>\n        <div\n          className=\"size-0 border-x-[7px] border-t-[8px] border-x-transparent\"\n          style={{ borderTopColor: RED }}\n        />\n      </div>\n\n      <input\n        aria-label=\"Timeline year\"\n        type=\"range\"\n        min={MIN}\n        max={MAX}\n        step={timelineBounds.step}\n        value={year}\n        onChange={(event) => onYearChange(Number(event.target.value))}\n        className=\"pointer-events-none absolute inset-x-0 bottom-0 h-[120px] opacity-0\"\n      />\n    </div>\n  );\n}\n",
      "type": "registry:component",
      "target": "app/old-maps/components/old-maps-timeline.tsx"
    },
    {
      "path": "src/registry/blocks/old-maps-timeline/components/results-sidebar.tsx",
      "content": "\"use client\";\n\nimport { useEffect, useRef } from \"react\";\nimport { MapPin, Search, X } from \"lucide-react\";\n\nimport { cn } from \"@/lib/utils\";\nimport { MapThumbnail } from \"./map-thumbnail\";\nimport type { HistoricalMapRecord } from \"../data\";\n\ntype ResultsSidebarProps = {\n  maps: HistoricalMapRecord[];\n  totalCount: number;\n  year: number;\n  query: string;\n  selectedMapId: string;\n  hoveredMapId: string | null;\n  onQueryChange: (value: string) => void;\n  onSelectMap: (id: string) => void;\n  onHoverMap: (id: string | null) => void;\n  onClose?: () => void;\n  className?: string;\n};\n\nexport function ResultsSidebar({\n  maps,\n  totalCount,\n  year,\n  query,\n  selectedMapId,\n  hoveredMapId,\n  onQueryChange,\n  onSelectMap,\n  onHoverMap,\n  onClose,\n  className,\n}: ResultsSidebarProps) {\n  const itemRefs = useRef(new Map<string, HTMLButtonElement | null>());\n\n  // Keep the active card in view as the timeline / map drive the selection.\n  useEffect(() => {\n    const node = itemRefs.current.get(selectedMapId);\n    node?.scrollIntoView({ block: \"nearest\" });\n  }, [selectedMapId]);\n\n  return (\n    <aside\n      className={cn(\n        \"bg-background flex h-full w-full flex-col border-r md:w-[360px]\",\n        className,\n      )}\n    >\n      <div className=\"space-y-3 border-b p-4\">\n        <div className=\"flex items-center justify-between gap-2\">\n          <div className=\"flex items-center gap-2\">\n            <span className=\"grid size-7 place-items-center rounded-md bg-[#ab1000] text-white\">\n              <MapPin className=\"size-4\" />\n            </span>\n            <div className=\"leading-tight\">\n              <p className=\"text-sm font-semibold tracking-tight\">\n                OldMapsOnline\n              </p>\n              <p className=\"text-muted-foreground text-[11px]\">\n                Historical map explorer\n              </p>\n            </div>\n          </div>\n          {onClose ? (\n            <button\n              type=\"button\"\n              aria-label=\"Close results\"\n              onClick={onClose}\n              className=\"hover:bg-muted text-muted-foreground grid size-8 place-items-center rounded-md md:hidden\"\n            >\n              <X className=\"size-4\" />\n            </button>\n          ) : null}\n        </div>\n\n        <div className=\"relative\">\n          <Search className=\"text-muted-foreground pointer-events-none absolute top-1/2 left-2.5 size-4 -translate-y-1/2\" />\n          <input\n            value={query}\n            onChange={(event) => onQueryChange(event.target.value)}\n            placeholder=\"Search places or cartographers\"\n            aria-label=\"Search maps\"\n            className=\"border-input bg-background focus-visible:ring-ring h-9 w-full rounded-md border pr-3 pl-8 text-sm shadow-sm outline-none focus-visible:ring-2\"\n          />\n        </div>\n\n        <div className=\"text-muted-foreground flex items-center justify-between text-xs\">\n          <span>\n            <span className=\"text-foreground font-medium\">{maps.length}</span>{\" \"}\n            of {totalCount} maps\n          </span>\n          <span>around {year}</span>\n        </div>\n      </div>\n\n      <div className=\"min-h-0 flex-1 overflow-y-auto\">\n        {maps.length === 0 ? (\n          <p className=\"text-muted-foreground p-6 text-center text-sm\">\n            No maps match this period. Try dragging the timeline or clearing the\n            search.\n          </p>\n        ) : (\n          <ul className=\"divide-y\">\n            {maps.map((map) => {\n              const selected = map.id === selectedMapId;\n              const hovered = map.id === hoveredMapId;\n              return (\n                <li key={map.id}>\n                  <button\n                    type=\"button\"\n                    ref={(node) => {\n                      itemRefs.current.set(map.id, node);\n                    }}\n                    onClick={() => onSelectMap(map.id)}\n                    onMouseEnter={() => onHoverMap(map.id)}\n                    onMouseLeave={() => onHoverMap(null)}\n                    onFocus={() => onHoverMap(map.id)}\n                    onBlur={() => onHoverMap(null)}\n                    className={cn(\n                      \"flex w-full gap-3 border-l-2 border-transparent px-4 py-3 text-left transition-colors\",\n                      hovered && !selected && \"bg-muted/60\",\n                      selected && \"border-l-[#ab1000] bg-[#ab1000]/10\",\n                    )}\n                  >\n                    <span\n                      className={cn(\n                        \"size-14 shrink-0 overflow-hidden rounded-sm border shadow-sm\",\n                        selected && \"ring-2 ring-[#ab1000]\",\n                      )}\n                    >\n                      <MapThumbnail seed={map.id} />\n                    </span>\n                    <span className=\"min-w-0 flex-1\">\n                      <span className=\"line-clamp-2 text-sm leading-snug font-medium\">\n                        {map.title}\n                      </span>\n                      <span className=\"text-muted-foreground mt-0.5 flex items-center gap-1.5 text-xs\">\n                        <span className=\"text-foreground tabular-nums\">\n                          {map.year}\n                        </span>\n                        <span aria-hidden>·</span>\n                        <span className=\"truncate\">{map.place}</span>\n                      </span>\n                      <span className=\"text-muted-foreground mt-0.5 block truncate text-xs\">\n                        {map.author}\n                      </span>\n                      <span className=\"text-muted-foreground/80 mt-1 flex items-center gap-1.5 text-[11px]\">\n                        <span className=\"bg-muted truncate rounded px-1.5 py-0.5\">\n                          {map.scale}\n                        </span>\n                        <span className=\"truncate\">{map.archive}</span>\n                      </span>\n                    </span>\n                  </button>\n                </li>\n              );\n            })}\n          </ul>\n        )}\n      </div>\n    </aside>\n  );\n}\n",
      "type": "registry:component",
      "target": "app/old-maps/components/results-sidebar.tsx"
    },
    {
      "path": "src/registry/blocks/old-maps-timeline/components/map-thumbnail.tsx",
      "content": "\"use client\";\n\nimport { useMemo } from \"react\";\n\nimport { cn } from \"@/lib/utils\";\n\n/**\n * A deterministic, parchment-styled \"old map\" thumbnail rendered entirely in\n * SVG. There are no external assets, so each result card gets a distinct,\n * stable illustration derived from its id — a stand-in for the scanned map\n * thumbnails OldMapsOnline shows in its results list.\n */\nfunction hashString(value: string) {\n  let hash = 2166136261;\n  for (let i = 0; i < value.length; i += 1) {\n    hash ^= value.charCodeAt(i);\n    hash = Math.imul(hash, 16777619);\n  }\n  return hash >>> 0;\n}\n\nfunction mulberry32(seed: number) {\n  let a = seed;\n  return () => {\n    a |= 0;\n    a = (a + 0x6d2b79f5) | 0;\n    let t = Math.imul(a ^ (a >>> 15), 1 | a);\n    t = (t + Math.imul(t ^ (t >>> 7), 61 | t)) ^ t;\n    return ((t ^ (t >>> 14)) >>> 0) / 4294967296;\n  };\n}\n\nexport function MapThumbnail({\n  seed,\n  className,\n}: {\n  seed: string;\n  className?: string;\n}) {\n  const { coast, rivers, graticule, hue } = useMemo(() => {\n    const rand = mulberry32(hashString(seed));\n    const size = 64;\n\n    // A wandering coastline that divides \"land\" from \"sea\".\n    const points: string[] = [];\n    let y = 14 + rand() * 14;\n    for (let x = 0; x <= size; x += 8) {\n      y += (rand() - 0.5) * 14;\n      y = Math.max(8, Math.min(size - 8, y));\n      points.push(`${x},${y.toFixed(1)}`);\n    }\n    const coast = `M0,${size} L0,${points[0].split(\",\")[1]} ${points\n      .map((p) => `L${p}`)\n      .join(\" \")} L${size},${size} Z`;\n\n    // A couple of meandering rivers.\n    const rivers: string[] = [];\n    const riverCount = 1 + Math.floor(rand() * 2);\n    for (let r = 0; r < riverCount; r += 1) {\n      let rx = 10 + rand() * (size - 20);\n      let ry = size;\n      let path = `M${rx.toFixed(1)},${ry}`;\n      while (ry > 6) {\n        ry -= 7 + rand() * 5;\n        rx += (rand() - 0.5) * 16;\n        rx = Math.max(4, Math.min(size - 4, rx));\n        path += ` L${rx.toFixed(1)},${ry.toFixed(1)}`;\n      }\n      rivers.push(path);\n    }\n\n    const graticule = [16, 32, 48];\n    const hue = 28 + Math.floor(rand() * 18); // warm sepia range\n    return { coast, rivers, graticule, hue };\n  }, [seed]);\n\n  return (\n    <svg\n      viewBox=\"0 0 64 64\"\n      className={cn(\"h-full w-full\", className)}\n      role=\"img\"\n      aria-hidden=\"true\"\n    >\n      <rect width=\"64\" height=\"64\" fill={`hsl(${hue} 44% 86%)`} />\n      <path d={coast} fill={`hsl(${hue} 34% 78%)`} />\n      {graticule.map((g) => (\n        <g key={g} stroke={`hsl(${hue} 30% 64%)`} strokeWidth=\"0.4\" opacity=\"0.5\">\n          <line x1={g} y1=\"0\" x2={g} y2=\"64\" />\n          <line x1=\"0\" y1={g} x2=\"64\" y2={g} />\n        </g>\n      ))}\n      {rivers.map((d, i) => (\n        <path\n          key={i}\n          d={d}\n          fill=\"none\"\n          stroke={`hsl(${hue} 36% 52%)`}\n          strokeWidth=\"0.9\"\n          strokeLinecap=\"round\"\n          opacity=\"0.8\"\n        />\n      ))}\n      <circle\n        cx=\"50\"\n        cy=\"14\"\n        r=\"5\"\n        fill=\"none\"\n        stroke={`hsl(${hue} 40% 40%)`}\n        strokeWidth=\"0.7\"\n        opacity=\"0.7\"\n      />\n      <path\n        d=\"M50,9 L51.4,14 L50,19 L48.6,14 Z\"\n        fill={`hsl(${hue} 40% 40%)`}\n        opacity=\"0.7\"\n      />\n      <rect\n        x=\"1\"\n        y=\"1\"\n        width=\"62\"\n        height=\"62\"\n        fill=\"none\"\n        stroke={`hsl(${hue} 38% 46%)`}\n        strokeWidth=\"1.4\"\n        opacity=\"0.65\"\n      />\n    </svg>\n  );\n}\n",
      "type": "registry:component",
      "target": "app/old-maps/components/map-thumbnail.tsx"
    },
    {
      "path": "src/registry/blocks/old-maps-timeline/components/map-footprints.tsx",
      "content": "\"use client\";\n\nimport { useEffect, useMemo } from \"react\";\nimport type MapLibreGL from \"maplibre-gl\";\n\nimport { useMap } from \"@/components/ui/map\";\nimport { footprintCollection, type HistoricalMapRecord } from \"../data\";\n\ntype MapFootprintsProps = {\n  maps: HistoricalMapRecord[];\n  selectedMapId: string;\n  hoveredMapId: string | null;\n  onSelectMap: (id: string) => void;\n  onHoverMap: (id: string | null) => void;\n};\n\nconst SOURCE_ID = \"old-maps-footprints\";\nconst FILL_ID = \"old-maps-footprints-fill\";\nconst LINE_ID = \"old-maps-footprints-line\";\n\n// OldMapsOnline palette — red for the active sheet, amber on hover, sepia ink\n// for the rest. Hard-coded so the explorer keeps its own identity.\nconst RED = \"#ab1000\";\nconst AMBER = \"#e7903a\";\nconst INK = \"#675c44\";\n\nconst stateColor: MapLibreGL.ExpressionSpecification = [\n  \"match\",\n  [\"get\", \"state\"],\n  \"selected\",\n  RED,\n  \"hovered\",\n  AMBER,\n  INK,\n];\nconst fillOpacity: MapLibreGL.ExpressionSpecification = [\n  \"match\",\n  [\"get\", \"state\"],\n  \"selected\",\n  0.22,\n  \"hovered\",\n  0.16,\n  0.05,\n];\nconst lineWidth: MapLibreGL.ExpressionSpecification = [\n  \"match\",\n  [\"get\", \"state\"],\n  \"selected\",\n  2.5,\n  \"hovered\",\n  1.75,\n  1,\n];\nconst lineOpacity: MapLibreGL.ExpressionSpecification = [\n  \"match\",\n  [\"get\", \"state\"],\n  \"selected\",\n  1,\n  \"hovered\",\n  0.9,\n  0.4,\n];\n\n/** Draws coverage rectangles for each historical map sheet on the basemap. */\nexport function MapFootprints({\n  maps,\n  selectedMapId,\n  hoveredMapId,\n  onSelectMap,\n  onHoverMap,\n}: MapFootprintsProps) {\n  const { map, isLoaded } = useMap();\n\n  const data = useMemo(\n    () => footprintCollection(maps, selectedMapId, hoveredMapId),\n    [maps, selectedMapId, hoveredMapId],\n  );\n\n  // Create the source + layers, and re-create them if the style reloads\n  // (e.g. on a light/dark theme switch, which discards custom layers).\n  useEffect(() => {\n    if (!isLoaded || !map) return;\n\n    const ensureLayers = () => {\n      if (!map.getSource(SOURCE_ID)) {\n        map.addSource(SOURCE_ID, { type: \"geojson\", data });\n      }\n      if (!map.getLayer(FILL_ID)) {\n        map.addLayer({\n          id: FILL_ID,\n          type: \"fill\",\n          source: SOURCE_ID,\n          paint: { \"fill-color\": stateColor, \"fill-opacity\": fillOpacity },\n        });\n      }\n      if (!map.getLayer(LINE_ID)) {\n        map.addLayer({\n          id: LINE_ID,\n          type: \"line\",\n          source: SOURCE_ID,\n          layout: { \"line-join\": \"round\" },\n          paint: {\n            \"line-color\": stateColor,\n            \"line-width\": lineWidth,\n            \"line-opacity\": lineOpacity,\n          },\n        });\n      }\n    };\n\n    ensureLayers();\n    map.on(\"styledata\", ensureLayers);\n\n    return () => {\n      map.off(\"styledata\", ensureLayers);\n      try {\n        if (map.getLayer(LINE_ID)) map.removeLayer(LINE_ID);\n        if (map.getLayer(FILL_ID)) map.removeLayer(FILL_ID);\n        if (map.getSource(SOURCE_ID)) map.removeSource(SOURCE_ID);\n      } catch {\n        // style already torn down — nothing to clean up\n      }\n    };\n    // eslint-disable-next-line react-hooks/exhaustive-deps\n  }, [isLoaded, map]);\n\n  // Push fresh state into the source whenever selection / hover / set changes.\n  useEffect(() => {\n    if (!isLoaded || !map) return;\n    const source = map.getSource(SOURCE_ID) as\n      | MapLibreGL.GeoJSONSource\n      | undefined;\n    source?.setData(data);\n  }, [isLoaded, map, data]);\n\n  // Interactions: clicking a footprint selects it, hovering highlights it.\n  useEffect(() => {\n    if (!isLoaded || !map) return;\n\n    const handleClick = (\n      event: MapLibreGL.MapMouseEvent & {\n        features?: MapLibreGL.MapGeoJSONFeature[];\n      },\n    ) => {\n      const id = event.features?.[0]?.properties?.id;\n      if (typeof id === \"string\") onSelectMap(id);\n    };\n    const handleMove = (\n      event: MapLibreGL.MapMouseEvent & {\n        features?: MapLibreGL.MapGeoJSONFeature[];\n      },\n    ) => {\n      const id = event.features?.[0]?.properties?.id;\n      map.getCanvas().style.cursor = \"pointer\";\n      if (typeof id === \"string\") onHoverMap(id);\n    };\n    const handleLeave = () => {\n      map.getCanvas().style.cursor = \"\";\n      onHoverMap(null);\n    };\n\n    map.on(\"click\", FILL_ID, handleClick);\n    map.on(\"mousemove\", FILL_ID, handleMove);\n    map.on(\"mouseleave\", FILL_ID, handleLeave);\n\n    return () => {\n      map.off(\"click\", FILL_ID, handleClick);\n      map.off(\"mousemove\", FILL_ID, handleMove);\n      map.off(\"mouseleave\", FILL_ID, handleLeave);\n    };\n  }, [isLoaded, map, onSelectMap, onHoverMap]);\n\n  return null;\n}\n",
      "type": "registry:component",
      "target": "app/old-maps/components/map-footprints.tsx"
    }
  ],
  "meta": {
    "iframeHeight": "780px"
  },
  "categories": [
    "history",
    "timeline"
  ],
  "type": "registry:block"
}
